{
 "mdsDat": {
 "x": [ 0.037169, 0.0090873, 0.01404, -0.075683, -0.062165, 0.012134, -0.07528, 0.12178, -0.006025, 0.024939 ],
"y": [ 0.054426, 0.0050421, -0.0070822, 0.099084, -0.018178, 0.0087198, -0.024484, 0.030326, -0.078955, -0.068898 ],
"topics": [ 1, 2, 3, 4, 5, 6, 7, 8, 9, 10 ],
"Freq": [ 12.329, 11.586, 10.255, 10.106, 9.9343, 9.4411, 9.3663, 9.2015, 8.9156,  8.866 ],
"cluster": [      1,      1,      1,      1,      1,      1,      1,      1,      1,      1 ] 
},
"tinfo": {
 "Term": [ "love", "rome", "england", "god", "beauti", "nobl", "marri", "madam", "signior", "ey", "105", "110", "115", "120", "125", "130", "135", "140", "145", "150", "bohemia", "aer", "andiron", "apart", "arrearag", "augustu", "backdoor", "backsid", "between", "briton", "cargo", "citadel", "compt", "gerard", "narbon", "rousillon", "salad", "asp", "pompeiu", "sicyon", "addeth", "amazeth", "astronomi", "barrenli", "bequest", "beseig", "bestowest", "bevel", "blunter", "bristli", "aesop", "aubrei", "awhi", "barnet", "bess", "bluntest", "bodg", "bonvil", "brotherlik", "butcherli", "ardour", "requiem", "spendthrift", "abstemi", "acquisit", "african", "aground", "and", "argier", "aspers", "accomplic", "agaz", "alton", "arc", "armagnac", "artoi", "attorneyship", "await", "bachelorship", "barter", "abi", "aegl", "antiopa", "asshead", "barki", "batti", "behowl", "bergomask", "briski", "buskin", "abaissiez", "accru", "adul", "aggriev", "agincourt", "ainsi", "alexand", "almshous", "ang", "angleterr", "abrawl", "abrooch", "accommodo", "achitophel", "aconitum", "administr", "africa", "alecto", "amurath", "aptest", "cesario", "l'envoi", "topa", "chooseth", "illyria", "madonna", "sola", "navarr", "messina", "bellario", "volsc", "corioli", "volscian", "cadwal", "shall", "polydor", "tarpeian", "thane", "cawdor", "fulvia", "birnam", "dunsinan", "isi", "cauldron", "glami", "collatin", "aemelia", "goldsmith", "collatinu", "syracusian", "epidamnum", "abbess", "montagu", "capulet", "syracusa", "derbi", "angier", "geffrei", "disinherit", "brittani", "montgomeri", "repossess", "breton", "phaethon", "chertsei", "denmark", "nuncl", "tuni", "sycorax", "danish", "polack", "voltimand", "incestu", "nunneri", "claribel", "saturnin", "beaufort", "ruler", "lionel", "southwel", "rapin", "andronici", "cometh", "gar", "thisbi", "pisa", "oman", "vill", "hern", "ganymed", "cambio", "licio", "wrestler", "tyre", "antenor", "tarsu", "saliqu", "greekish", "mytilen", "aunchient", "seigneur", "antioch", "fingr", "colevil", "sherri", "consumpt", "foremost", "apoplexi", "athenian", "fub", "gravi", "john", "nightwork", "jew", "austria", "britain", "cypru", "egypt", "le", "milford", "consul", "thisb", "trojan", "adoni", "empress", "vou", "protector", "sicilia", "leek", "hereford", "bulli", "hal", "capitol", "senat", "id", "handkerchief", "regent", "commonw", "moor", "dover", "fairi", "scot", "tiber", "senior", "thursdai", "emperor", "grecian", "beauti", "realm", "buck", "shout", "juda", "grandam", "stabb", "monster", "napl", "quoth", "greek", "norwai", "basket", "fidel", "philippi", "ducat", "son", "troi", "athen", "love", "tower", "brook", "willow", "woe", "crown", "swagger", "ey", "daughter", "padua", "wit", "item", "chain", "slew", "ireland", "lancast", "inn", "love", "england", "rome", "honor", "blood", "god", "gold", "ladyship", "death", "island", "friend", "signior", "marri", "soul", "harri", "letter", "report", "nobl", "count", "night", "land", "madam", "madam", "busi", "england", "sweet", "hand", "love", "life", "dai", "traitor", "hous", "fair", "fair", "god", "natur", "youth", "night", "sweet", "heaven", "love", "sister", "prai", "plai", "death", "woman", "prai", "mad", "husband", "god", "rome", "hear", "light", "fortun", "word", "heaven", "dai", "bear", "ey", "true", "heart", "hand", "heaven", "live", "love", "grace", "hear", "natur", "peac", "fear", "love", "heart", "tent", "heart", "nobl", "hand", "heart", "heart", "god", "signior", "death", "death", "night", "poor", "fair", "ey", "faith", "word", "leav", "sweet", "love", "live", "plai", "heart", "hear", "dai", "fear", "arm", "love", "blood", "hear", "prai", "stand", "hear", "live", "heart", "dai", "arm", "dai", "true", "sweet", "word", "love", "world", "life", "fear", "life", "ey", "hand", "heart", "love", "hand", "dai", "live", "friend", "blood", "word", "true", "heart", "fear", "god" ],
"logprob": [     10,      9,      8,      7,      6,      5,      4,      3,      2,      1, -10.326, -10.326, -10.326, -10.326, -10.326, -10.326, -10.326, -10.326, -10.326, -10.326, -7.085, -9.6499, -10.343, -10.343, -10.343, -8.7337, -10.343, -10.343, -9.2445, -7.3474, -8.2507, -8.2507, -9.098, -9.098, -9.098, -7.6317, -9.098, -9.098, -9.098, -9.098, -10.156, -10.156, -10.156, -10.156, -10.156, -10.156, -10.156, -10.156, -10.156, -9.4632, -10.299, -10.299, -10.299, -9.6062, -10.299, -10.299, -10.299, -10.299, -10.299, -10.299, -9.4045, -9.4045, -9.4045, -10.098, -10.098, -10.098, -10.098, -10.098, -9.4045, -10.098, -10.154, -10.154, -10.154, -9.4608, -9.0553, -10.154, -10.154, -9.0553, -10.154, -10.154, -9.369, -10.062, -10.062, -10.062, -10.062, -10.062, -10.062, -9.369, -10.062, -10.062, -10.057, -10.057, -10.057, -10.057, -8.6704, -9.3636, -10.057, -10.057, -10.057, -10.057, -10.069, -10.069, -10.069, -10.069, -10.069, -10.069, -10.069, -10.069, -9.3757, -10.069, -7.4358, -7.5536, -7.5536, -7.9283, -8.0236, -8.0236, -8.0236, -8.129, -8.129, -8.129, -7.3485, -7.4528, -8.0407, -8.3972, -8.5513, -8.7337, -8.7341, -6.7626, -7.1521, -7.3063, -7.894, -7.9994, -8.1172, -8.1172, -8.1172, -6.9375, -7.3838, -7.7599, -8.077, -8.077, -8.2105, -8.547, -8.547, -8.547, -8.7701, -6.9671, -7.7344, -8.1021, -8.5075, -8.6899, -8.913, -8.913, -8.913, -8.913, -9.2007, -7.0066, -7.2644, -7.9004, -8.1517, -8.3059, -8.4882, -8.4882, -8.4882, -8.4882, -8.7113, -7.3814, -7.589, -8.208, -8.5445, -8.7676, -8.7676, -8.7676, -8.7676, -6.6282, -6.6949, -7.4231, -7.5773, -7.7596, -7.865, -7.9827, -8.1163, -8.1163, -8.1163, -6.8794, -7.5718, -7.2872, -7.8595, -7.8595, -7.6614, -7.9773, -7.9773, -7.8616, -8.1108, -7.3608, -8.4594,  -8.46,  -8.46, -8.6826, -8.6826, -8.9703, -8.9703, -8.9703, -8.9703, -6.0495, -7.2083, -6.9758, -7.0186, -6.4124, -7.0122, -7.5099, -6.7878, -7.1177,  -6.32, -7.3232, -6.4163, -6.8379, -6.3253, -7.7781, -7.2235, -6.7782, -7.1718, -6.4946, -6.5964, -5.962, -8.2079, -6.7959, -7.3159, -7.9567, -6.1088, -7.6997, -6.8041, -6.9754, -8.1232, -6.5805, -7.5219, -6.0191, -6.7634, -5.1587, -6.4989, -7.1718, -6.6985, -7.6182, -7.2083, -7.8144, -6.0739, -7.0531, -6.0632, -6.3201, -7.6144, -6.8433, -8.0405, -7.7084, -6.7201, -5.8769, -5.9987, -6.6677, -3.7951, -6.5502, -6.0548, -7.2391, -5.6675, -5.408, -7.3612, -4.3759, -6.7306, -6.9267, -5.1954, -7.1907, -6.4145, -7.1276, -7.1423, -6.3448, -7.627, -3.8934, -5.7062, -5.489, -5.1334, -5.1343, -4.648, -5.7958, -6.9973, -4.9384, -7.0531, -4.8703, -6.2611, -5.0244, -5.2963, -5.9954, -5.658, -6.1524, -5.1504, -6.3217, -4.9562, -5.7773, -5.4835, -5.437, -5.9088, -5.6497, -5.1751, -4.9154, -4.1587, -5.2662, -4.9234, -5.8983, -5.2612, -5.232, -5.0915, -4.9058, -5.5683, -5.8005, -5.1641, -5.1005, -5.3193, -4.5433, -6.0911, -5.0426, -5.735, -5.0628, -5.4225, -5.4119, -5.8513, -5.5082, -4.8917, -5.7547, -5.3007, -5.6154, -5.562, -5.3155, -5.4454, -5.0371, -5.3635, -5.1922, -5.5075, -5.0058, -5.038, -5.3851, -5.2223, -4.8623, -5.5547, -5.2245, -5.6551, -5.5517, -5.4694, -4.7444, -5.1044, -6.2587, -5.1518, -5.624, -5.2743, -5.2194, -5.2493, -5.1409, -6.0804, -5.4893, -5.2259, -5.4923, -5.6378, -5.445, -5.392, -5.705, -5.3277, -5.5962, -5.3719, -4.9899, -5.2308, -5.6655, -5.3759, -5.3535, -5.2507, -5.2894, -5.5921, -5.1643, -5.5648, -5.4326, -5.5702, -5.4129, -5.495, -5.4139, -5.182, -5.3587, -5.7069, -5.2162, -5.4579, -5.5756, -5.4788, -5.1107, -5.6078, -5.4596, -5.5479, -5.5616, -5.5011, -5.4645, -5.5077, -5.2885, -5.5415, -5.4623, -5.558, -5.5721, -5.5456, -5.5272, -5.6774, -5.4675, -5.6741, -5.4652 ],
"loglift": [     10,      9,      8,      7,      6,      5,      4,      3,      2,      1, 2.0932, 2.0932, 2.0932, 2.0932, 2.0932, 2.0932, 2.0932, 2.0932, 2.0932, 2.0932, 2.1554, 2.1554, 2.1554, 2.1554, 2.1554, 2.1554, 2.1554, 2.1554, 2.1554, 2.1554, 2.2774, 2.2774, 2.2774, 2.2774, 2.2774, 2.2774, 2.2774, 2.2774, 2.2774, 2.2774, 2.2921, 2.2921, 2.2921, 2.2921, 2.2921, 2.2921, 2.2921, 2.2921, 2.2921, 2.2921, 2.3092, 2.3092, 2.3092, 2.3092, 2.3092, 2.3092, 2.3092, 2.3092, 2.3092, 2.3092, 2.3601, 2.3601, 2.3601, 2.3601, 2.3601, 2.3601, 2.3601, 2.3601, 2.3601, 2.3601,  2.368,  2.368,  2.368,  2.368,  2.368,  2.368,  2.368,  2.368,  2.368,  2.368, 2.3858, 2.3858, 2.3858, 2.3858, 2.3858, 2.3858, 2.3858, 2.3858, 2.3858, 2.3858, 2.4174, 2.4174, 2.4174, 2.4174, 2.4174, 2.4174, 2.4174, 2.4174, 2.4174, 2.4174, 2.4229, 2.4229, 2.4229, 2.4229, 2.4229, 2.4229, 2.4229, 2.4229, 2.4229, 2.4229, 2.0932, 2.0932, 2.0932, 2.0932, 2.0932, 2.0932, 2.0932, 2.0932, 2.0932, 2.0932, 2.1543, 2.1553, 2.1552, 2.1554, 2.1554, 2.1554,  2.155, 2.2774, 2.2774, 2.2774, 2.2774, 2.2774, 2.2774, 2.2774, 2.2774, 2.2921, 2.2921, 2.2906, 2.2921, 2.2921, 2.2921, 2.2921,  2.292,  2.292, 2.2921, 2.3092, 2.3092, 2.3092, 2.3092, 2.3092, 2.3092, 2.3092, 2.3092, 2.3092, 2.3092, 2.3601, 2.3601, 2.3601, 2.3601, 2.3601, 2.3601, 2.3601, 2.3601, 2.3601, 2.3601,  2.368,  2.368,  2.368,  2.368,  2.368,  2.368,  2.368,  2.368, 2.3858, 2.3858, 2.3858, 2.3858, 2.3858, 2.3858, 2.3858, 2.3858, 2.3858, 2.3858, 2.4167, 2.4174, 2.4144, 2.4174, 2.4174, 2.4149, 2.4174, 2.4174, 2.4154, 2.4174, 2.4229, 2.4229, 2.4224, 2.4223, 2.4229, 2.4229, 2.4229, 2.4229, 2.4229, 2.4229, 2.0416, 2.2585, 2.0867, 2.2376,   2.21,  2.373,  2.104, 2.0439, 2.3331, 2.3257, 2.1845, 2.1824, 2.3363, 2.1535, 2.0829, 2.3587, 2.1695, 2.2822, 2.2684, 2.1841, 2.0996,  2.347, 2.1277, 2.2008, 2.2603, 1.9933, 2.2087, 2.1855, 2.2833,  2.287,  2.148, 2.0989,   1.85, 2.2415, 1.5512, 1.9245, 2.2349, 1.9914, 1.9796, 1.9135, 2.0528, 1.8276,  2.026, 1.6991,  2.113, 2.1386, 2.1425, 2.0554, 2.1437, 1.6698, 1.6052,  1.982, 1.8174,  0.694, 1.5399, 1.8761, 2.0179, 1.4054,  1.134,  2.026, 0.9502, 1.7191,  2.148,  1.006, 1.7819, 1.6649,  1.681, 1.9492, 1.5723, 2.0892, 0.5957, 1.0882, 1.2726, 0.7912, 0.7814, 0.6953, 1.2313, 1.6477, 0.6474, 1.7628, 0.7816, 1.2757, 1.1556, 0.8035, 1.7313, 0.9185, 1.1038, 0.8152, 1.2508, 0.6362, 1.0453, 0.7219, 0.7685, 0.9499, 1.1447, 0.5081, 0.4688, 0.3303,  0.371, 0.4552,  1.254, 1.0145,  0.491, 0.6315, 0.4375,  0.683, 0.8698, 0.4283, 0.5828, 0.4163, -0.0542, 0.9745,  0.738, 0.6908, 0.5229, 1.0002, 0.3687, 0.7778, 1.0468, 0.4516, 1.0069, 0.2341, 0.9408, 0.6636, 0.2928, 0.2901, 0.3414, 0.4742, 0.1338, 0.2236, 0.2651, 0.3462, 0.3505, 0.3464, -0.3732, 0.3981, 0.3102, 0.5962,  0.609, 0.1661, -0.2553, 0.1665, 1.6111, 0.1191, 0.3416, 0.1099, 0.0514, 0.0216, 0.2024, 1.4563, 0.0965, 0.3599, 0.1001, 0.3171,  0.278, -0.0659, 0.6395, 0.2805, 0.2213, 0.3114, -0.5008, 0.3378, 0.7603, -0.105, 0.1812, 0.1278, 0.3461, 0.6793, -0.6752, 0.3508, 0.1022, 0.2103, 0.4014, 0.0397, 0.1547, 0.0888, 0.0198, 0.5646, 0.1624, 0.2732, 0.1077, 0.1295, -0.6217, 0.3033, 0.1775, 0.0876, 0.0756, -0.175, -0.0803, -0.2368, -0.7995, -0.1573, -0.0838, 0.0107, 0.0797, 0.3701,  0.081, 0.0538, -0.1966, -0.0386, -0.1219 ],
"Freq": [   1063,    109,    106,    452,    115,    242,    196,    191,     50,    460, 0.38256, 0.38256, 0.38256, 0.38256, 0.38256, 0.38256, 0.38256, 0.38256, 0.38256, 0.38256,  9.191,  0.707, 0.3535, 0.3535, 0.3535, 1.7675, 0.3535, 0.3535, 1.0605,   7.07, 2.5356, 2.5356, 1.0867, 1.0867, 1.0867, 4.7089, 1.0867, 1.0867, 1.0867, 1.0867, 0.37163, 0.37163, 0.37163, 0.37163, 0.37163, 0.37163, 0.37163, 0.37163, 0.37163, 0.74325, 0.31667, 0.31667, 0.31667, 0.63334, 0.31667, 0.31667, 0.31667, 0.31667, 0.31667, 0.31667, 0.73638, 0.73638, 0.73638, 0.36819, 0.36819, 0.36819, 0.36819, 0.36819, 0.73638, 0.36819, 0.34528, 0.34528, 0.34528, 0.69056, 1.0358, 0.34528, 0.34528, 1.0358, 0.34528, 0.34528, 0.7436, 0.3718, 0.3718, 0.3718, 0.3718, 0.3718, 0.3718, 0.7436, 0.3718, 0.3718, 0.36221, 0.36221, 0.36221, 0.36221, 1.4489, 0.72443, 0.36221, 0.36221, 0.36221, 0.36221, 0.35585, 0.35585, 0.35585, 0.35585, 0.35585, 0.35585, 0.35585, 0.35585, 0.71171, 0.35585,  6.886, 6.1209, 6.1209, 4.2081, 3.8256, 3.8256, 3.8256,  3.443,  3.443,  3.443, 7.0623, 6.3624, 3.5343, 2.4745,  2.121, 1.7675, 1.7668, 11.229, 7.6067, 6.5201, 3.6223,   3.26, 2.8978, 2.8978, 2.8978, 9.2907,  5.946, 4.0821,  2.973,  2.973, 2.6014, 1.8581, 1.8581,  1.858, 1.4865, 8.8668, 4.1167,   2.85,    1.9, 1.5834, 1.2667, 1.2667, 1.2667, 1.2667, 0.95001, 8.1002, 6.2593, 3.3137, 2.5773, 2.2091,  1.841,  1.841,  1.841,  1.841, 1.4728, 5.5245, 4.4886,  2.417, 1.7264, 1.3811, 1.3811, 1.3811, 1.3811, 11.526, 10.782, 5.2052, 4.4616,  3.718, 3.3462, 2.9744, 2.6026, 2.6026, 2.6026, 8.6868, 4.3466, 5.7778, 3.2599, 3.2599, 3.9741, 2.8977, 2.8977, 3.2532, 2.5355, 5.3378, 1.7793, 1.7784, 1.7782, 1.4234, 1.4234, 1.0676, 1.0676, 1.0676, 1.0676, 27.544, 6.9668, 10.251, 8.6934, 15.938, 7.6065, 6.0095, 12.371, 7.0642, 15.199, 6.3177, 14.502, 9.0553, 15.883, 4.5955, 6.1576, 10.098, 6.6924, 12.764, 11.464, 21.621, 2.2882, 10.861, 5.8981, 3.1075, 21.593, 4.0501, 9.6667,  7.892, 2.4904, 12.089, 5.1789, 21.574, 9.7553, 55.029, 13.351, 6.6924, 10.351, 5.7384, 6.9668, 3.8001, 20.585,  7.732, 22.272, 15.198, 4.4111, 9.2949,  3.535, 3.7705, 14.086,  24.87, 20.958, 10.675,  262.5, 13.453,  20.45, 6.9733, 33.084, 42.157, 5.3358, 120.38, 10.675, 8.5513, 64.709, 8.7988, 15.675, 7.5517, 7.0166, 14.744, 4.0903, 195.03, 31.287, 36.653, 64.706,  55.43, 80.449,  25.53, 10.676, 67.427,  7.732, 64.417, 22.293, 57.307, 47.141, 21.027, 40.746, 23.354, 48.677, 20.981, 67.382, 29.141, 48.512, 42.274, 24.281, 31.213, 66.036, 68.992, 136.19,  56.66, 68.445, 24.342, 45.222, 62.383, 58.851, 69.659, 34.131, 35.333, 55.539, 58.326, 43.782, 103.32, 20.234, 56.273, 28.889, 56.132, 38.485, 48.977, 25.717, 35.325, 63.403, 26.601, 54.738, 34.851, 37.304, 57.389,  47.36, 54.823, 39.336, 64.918, 44.508, 64.118, 57.546, 44.526, 50.761, 69.146, 34.596, 45.201, 33.988, 32.589, 46.237, 81.859, 53.847, 16.159, 48.613, 39.615, 49.744, 63.175, 51.003, 51.916, 19.932, 45.329, 51.453, 36.827, 31.838, 36.459, 40.712, 28.112, 40.768, 40.733, 40.483, 57.473, 51.197, 30.182, 41.373, 41.233, 44.031, 47.466, 33.063, 62.734, 32.343, 42.459, 34.065,  37.44, 36.724, 39.513, 52.847, 41.754,  28.06, 51.954, 49.769, 31.997, 36.379, 50.648, 35.636, 37.748, 37.835,  34.36, 34.471, 36.903, 34.245,  44.79, 33.105,  49.55, 42.318, 36.929, 34.638,  35.28,   28.9, 36.792, 28.994, 49.408 ],
"Total": [   1063,    109,    106,    452,    115,    242,    196,    191,     50,    460, 0.38256, 0.38256, 0.38256, 0.38256, 0.38256, 0.38256, 0.38256, 0.38256, 0.38256, 0.38256,  9.191,  0.707, 0.3535, 0.3535, 0.3535, 1.7675, 0.3535, 0.3535, 1.0605,   7.07, 2.5356, 2.5356, 1.0867, 1.0867, 1.0867, 4.7089, 1.0867, 1.0867, 1.0867, 1.0867, 0.37163, 0.37163, 0.37163, 0.37163, 0.37163, 0.37163, 0.37163, 0.37163, 0.37163, 0.74325, 0.31667, 0.31667, 0.31667, 0.63334, 0.31667, 0.31667, 0.31667, 0.31667, 0.31667, 0.31667, 0.73638, 0.73638, 0.73638, 0.36819, 0.36819, 0.36819, 0.36819, 0.36819, 0.73638, 0.36819, 0.34528, 0.34528, 0.34528, 0.69056, 1.0358, 0.34528, 0.34528, 1.0358, 0.34528, 0.34528, 0.7436, 0.3718, 0.3718, 0.3718, 0.3718, 0.3718, 0.3718, 0.7436, 0.3718, 0.3718, 0.36221, 0.36221, 0.36221, 0.36221, 1.4489, 0.72443, 0.36221, 0.36221, 0.36221, 0.36221, 0.35585, 0.35585, 0.35585, 0.35585, 0.35585, 0.35585, 0.35585, 0.35585, 0.71171, 0.35585,  6.886, 6.1209, 6.1209, 4.2081, 3.8256, 3.8256, 3.8256,  3.443,  3.443,  3.443,   7.07,  6.363,  3.535, 2.4745,  2.121, 1.7675, 1.7675, 11.229, 7.6067, 6.5201, 3.6223,   3.26, 2.8978, 2.8978, 2.8978, 9.2907,  5.946, 4.0879,  2.973,  2.973, 2.6014, 1.8581, 1.8581, 1.8581, 1.4865, 8.8668, 4.1167,   2.85,    1.9, 1.5834, 1.2667, 1.2667, 1.2667, 1.2667, 0.95001, 8.1002, 6.2593, 3.3137, 2.5773, 2.2091,  1.841,  1.841,  1.841,  1.841, 1.4728, 5.5245, 4.4886,  2.417, 1.7264, 1.3811, 1.3811, 1.3811, 1.3811, 11.526, 10.782, 5.2052, 4.4616,  3.718, 3.3462, 2.9744, 2.6026, 2.6026, 2.6026,  8.693, 4.3466,  5.795, 3.2599, 3.2599, 3.9841, 2.8977, 2.8977, 3.2598, 2.5355, 5.3378, 1.7793, 1.7793, 1.7793, 1.4234, 1.4234, 1.0676, 1.0676, 1.0676, 1.0676, 29.005,  7.329, 10.979, 9.0469,  17.05, 7.9518, 6.3262, 13.831, 7.4467, 16.658, 7.0347,  17.46, 9.8204, 19.683, 4.9408, 6.5294, 12.315, 7.4228, 14.814, 14.557, 29.875, 2.4686, 12.616, 6.9716,  3.461, 28.689, 4.7121, 11.811, 9.0243, 2.8531, 15.335, 6.2824, 36.218, 11.631, 115.43, 20.804, 7.7824, 15.937, 6.4289, 10.348, 4.9104, 35.062, 10.799, 40.298, 20.605, 5.5049, 11.855, 3.9068, 4.9852, 21.512, 53.333, 32.391,  19.56, 1063.7, 29.033, 34.044, 9.0399, 80.292, 136.53, 7.9357,  460.6, 20.266, 10.847, 191.93, 12.013, 29.349, 14.153, 10.667,  34.52, 5.7105, 1063.7, 106.08, 109.62, 253.16, 255.43, 452.71, 84.059,  16.67, 355.26,  14.05, 332.54, 50.495,  196.1, 212.47, 41.757, 131.91,  66.84, 242.97, 48.718, 352.92, 103.13, 191.16, 191.16, 99.472, 106.08, 322.25, 434.59, 1063.7, 337.46, 437.04, 74.164,  178.2, 309.67, 309.67, 452.71,  182.6, 120.09, 352.92, 322.25, 305.84, 1063.7, 80.876, 292.38, 153.35, 355.26, 153.84, 292.38, 125.14, 134.78, 452.71, 109.62, 373.84, 134.61, 187.34, 347.35, 305.84, 437.04, 276.14,  460.6, 307.17, 486.74, 434.59, 305.84, 361.38, 1063.7,  246.1, 373.84,  182.6, 199.91, 338.01, 1063.7, 486.74, 36.189, 486.74, 242.97, 434.59, 486.74, 486.74, 452.71, 50.495, 355.26, 355.26, 352.92,  245.6, 309.67,  460.6, 166.34, 347.35, 281.77, 322.25, 1063.7, 361.38, 153.35, 486.74, 373.84, 437.04, 338.01, 178.96, 1063.7, 255.43, 373.84, 292.38, 282.67, 373.84, 361.38, 486.74, 437.04, 178.96, 437.04, 307.17, 322.25, 347.35, 1063.7, 256.58, 337.46, 338.01, 337.46,  460.6, 434.59, 486.74, 1063.7, 434.59, 437.04, 361.38, 332.54, 255.43, 347.35, 307.17, 486.74, 338.01, 452.71 ],
"Category": [ "Default", "Default", "Default", "Default", "Default", "Default", "Default", "Default", "Default", "Default", "Topic1", "Topic1", "Topic1", "Topic1", "Topic1", "Topic1", "Topic1", "Topic1", "Topic1", "Topic1", "Topic2", "Topic2", "Topic2", "Topic2", "Topic2", "Topic2", "Topic2", "Topic2", "Topic2", "Topic2", "Topic3", "Topic3", "Topic3", "Topic3", "Topic3", "Topic3", "Topic3", "Topic3", "Topic3", "Topic3", "Topic4", "Topic4", "Topic4", "Topic4", "Topic4", "Topic4", "Topic4", "Topic4", "Topic4", "Topic4", "Topic5", "Topic5", "Topic5", "Topic5", "Topic5", "Topic5", "Topic5", "Topic5", "Topic5", "Topic5", "Topic6", "Topic6", "Topic6", "Topic6", "Topic6", "Topic6", "Topic6", "Topic6", "Topic6", "Topic6", "Topic7", "Topic7", "Topic7", "Topic7", "Topic7", "Topic7", "Topic7", "Topic7", "Topic7", "Topic7", "Topic8", "Topic8", "Topic8", "Topic8", "Topic8", "Topic8", "Topic8", "Topic8", "Topic8", "Topic8", "Topic9", "Topic9", "Topic9", "Topic9", "Topic9", "Topic9", "Topic9", "Topic9", "Topic9", "Topic9", "Topic10", "Topic10", "Topic10", "Topic10", "Topic10", "Topic10", "Topic10", "Topic10", "Topic10", "Topic10", "Topic1", "Topic1", "Topic1", "Topic1", "Topic1", "Topic1", "Topic1", "Topic1", "Topic1", "Topic1", "Topic2", "Topic2", "Topic2", "Topic2", "Topic2", "Topic2", "Topic2", "Topic3", "Topic3", "Topic3", "Topic3", "Topic3", "Topic3", "Topic3", "Topic3", "Topic4", "Topic4", "Topic4", "Topic4", "Topic4", "Topic4", "Topic4", "Topic4", "Topic4", "Topic4", "Topic5", "Topic5", "Topic5", "Topic5", "Topic5", "Topic5", "Topic5", "Topic5", "Topic5", "Topic5", "Topic6", "Topic6", "Topic6", "Topic6", "Topic6", "Topic6", "Topic6", "Topic6", "Topic6", "Topic6", "Topic7", "Topic7", "Topic7", "Topic7", "Topic7", "Topic7", "Topic7", "Topic7", "Topic8", "Topic8", "Topic8", "Topic8", "Topic8", "Topic8", "Topic8", "Topic8", "Topic8", "Topic8", "Topic9", "Topic9", "Topic9", "Topic9", "Topic9", "Topic9", "Topic9", "Topic9", "Topic9", "Topic9", "Topic10", "Topic10", "Topic10", "Topic10", "Topic10", "Topic10", "Topic10", "Topic10", "Topic10", "Topic10", "Topic1", "Topic5", "Topic2", "Topic3", "Topic3", "Topic9", "Topic2", "Topic2", "Topic8", "Topic9", "Topic4", "Topic7", "Topic9", "Topic7", "Topic2", "Topic9", "Topic7", "Topic8", "Topic9", "Topic10", "Topic10", "Topic10", "Topic3", "Topic7", "Topic7", "Topic3", "Topic6", "Topic8", "Topic9", "Topic10", "Topic8", "Topic4", "Topic7", "Topic9", "Topic4", "Topic7", "Topic8", "Topic10", "Topic1", "Topic5", "Topic5", "Topic6", "Topic6", "Topic4", "Topic9", "Topic6", "Topic8", "Topic2", "Topic10", "Topic1", "Topic7", "Topic9", "Topic10", "Topic1", "Topic5", "Topic8", "Topic3", "Topic4", "Topic5", "Topic10", "Topic4", "Topic6", "Topic8", "Topic1", "Topic1", "Topic4", "Topic5", "Topic7", "Topic10", "Topic10", "Topic4", "Topic5", "Topic7", "Topic2", "Topic5", "Topic10", "Topic10", "Topic1", "Topic5", "Topic6", "Topic10", "Topic1", "Topic8", "Topic5", "Topic9", "Topic1", "Topic2", "Topic10", "Topic1", "Topic4", "Topic5", "Topic1", "Topic3", "Topic6", "Topic7", "Topic1", "Topic5", "Topic8", "Topic2", "Topic5", "Topic7", "Topic8", "Topic1", "Topic4", "Topic5", "Topic6", "Topic1", "Topic3", "Topic4", "Topic6", "Topic3", "Topic6", "Topic8", "Topic6", "Topic7", "Topic8", "Topic2", "Topic6", "Topic8", "Topic9", "Topic10", "Topic2", "Topic4", "Topic3", "Topic1", "Topic2", "Topic9", "Topic10", "Topic1", "Topic2", "Topic4", "Topic7", "Topic3", "Topic5", "Topic6", "Topic6", "Topic10", "Topic3", "Topic10", "Topic2", "Topic5", "Topic7", "Topic9", "Topic10", "Topic2", "Topic3", "Topic1", "Topic3", "Topic7", "Topic8", "Topic2", "Topic4", "Topic6", "Topic6", "Topic9", "Topic6", "Topic9", "Topic10", "Topic2", "Topic8", "Topic9", "Topic4", "Topic8", "Topic6", "Topic8", "Topic10", "Topic5", "Topic7", "Topic2", "Topic9", "Topic3", "Topic6", "Topic10", "Topic6", "Topic7", "Topic5", "Topic7", "Topic9", "Topic4", "Topic1", "Topic9", "Topic8", "Topic10", "Topic3", "Topic7", "Topic3", "Topic6", "Topic9", "Topic8", "Topic9", "Topic7", "Topic9", "Topic1", "Topic2", "Topic3", "Topic7", "Topic7", "Topic9", "Topic8", "Topic9", "Topic1" ] 
},
"token.table": {
 "Term": [ "abbess", "abi", "adoni", "aemelia", "aer", "agincourt", "ainsi", "amurath", "andronici", "angier", "antenor", "antioch", "apoplexi", "arc", "ardour", "argier", "arm", "arm", "arm", "arm", "arm", "arm", "arm", "arm", "arm", "arm", "armagnac", "asp", "athen", "athen", "athen", "athenian", "augustu", "aunchient", "austria", "await", "barnet", "basket", "basket", "basket", "bear", "bear", "bear", "bear", "bear", "bear", "bear", "bear", "bear", "bear", "beaufort", "beauti", "beauti", "beauti", "beauti", "beauti", "beauti", "beauti", "beauti", "beauti", "bellario", "bergomask", "between", "birnam", "blood", "blood", "blood", "blood", "blood", "blood", "blood", "blood", "blood", "blood", "bohemia", "breton", "bristli", "britain", "briton", "brittani", "brook", "brook", "brook", "brook", "brook", "brook", "brook", "brook", "buck", "bulli", "busi", "busi", "busi", "busi", "busi", "busi", "busi", "busi", "busi", "busi", "cadwal", "cambio", "capitol", "capitol", "capitol", "capulet", "cargo", "cauldron", "cawdor", "cesario", "chain", "chain", "chain", "chain", "chain", "chain", "chain", "chain", "chain", "chertsei", "chooseth", "citadel", "claribel", "colevil", "collatin", "collatinu", "cometh", "commonw", "compt", "consul", "consul", "consumpt", "corioli", "count", "count", "count", "count", "count", "count", "count", "crown", "crown", "crown", "crown", "crown", "crown", "crown", "crown", "crown", "crown", "cypru", "dai", "dai", "dai", "dai", "dai", "dai", "dai", "dai", "dai", "dai", "danish", "daughter", "daughter", "daughter", "daughter", "daughter", "daughter", "daughter", "daughter", "daughter", "death", "death", "death", "death", "death", "death", "death", "death", "death", "death", "denmark", "derbi", "disinherit", "dover", "ducat", "ducat", "ducat", "ducat", "ducat", "dunsinan", "egypt", "egypt", "emperor", "emperor", "emperor", "emperor", "emperor", "emperor", "emperor", "emperor", "empress", "empress", "empress", "empress", "england", "england", "england", "england", "england", "england", "england", "england", "epidamnum", "ey", "ey", "ey", "ey", "ey", "ey", "ey", "ey", "ey", "ey", "fair", "fair", "fair", "fair", "fair", "fair", "fair", "fair", "fair", "fair", "fairi", "fairi", "faith", "faith", "faith", "faith", "faith", "faith", "faith", "faith", "faith", "faith", "fear", "fear", "fear", "fear", "fear", "fear", "fear", "fear", "fear", "fear", "fidel", "fingr", "foremost", "fortun", "fortun", "fortun", "fortun", "fortun", "fortun", "fortun", "fortun", "fortun", "fortun", "friend", "friend", "friend", "friend", "friend", "friend", "friend", "friend", "friend", "friend", "fub", "fulvia", "ganymed", "gar", "geffrei", "gerard", "glami", "god", "god", "god", "god", "god", "god", "god", "god", "god", "god", "gold", "gold", "gold", "gold", "gold", "gold", "gold", "gold", "gold", "gold", "goldsmith", "grace", "grace", "grace", "grace", "grace", "grace", "grace", "grace", "grace", "grace", "grandam", "grandam", "grandam", "gravi", "grecian", "grecian", "greek", "greek", "greek", "greek", "greek", "greekish", "hal", "hal", "hand", "hand", "hand", "hand", "hand", "hand", "hand", "hand", "hand", "hand", "handkerchief", "handkerchief", "harri", "harri", "harri", "harri", "hear", "hear", "hear", "hear", "hear", "hear", "hear", "hear", "hear", "hear", "heart", "heart", "heart", "heart", "heart", "heart", "heart", "heart", "heart", "heart", "heaven", "heaven", "heaven", "heaven", "heaven", "heaven", "heaven", "heaven", "heaven", "heaven", "hereford", "hereford", "hereford", "hern", "honor", "honor", "honor", "honor", "honor", "honor", "honor", "honor", "honor", "honor", "hous", "hous", "hous", "hous", "hous", "hous", "hous", "hous", "hous", "hous", "husband", "husband", "husband", "husband", "husband", "husband", "husband", "husband", "husband", "husband", "id", "illyria", "incestu", "inn", "inn", "ireland", "ireland", "ireland", "ireland", "isi", "island", "island", "island", "island", "island", "item", "item", "item", "item", "jew", "jew", "john", "juda", "juda", "l'envoi", "ladyship", "ladyship", "ladyship", "ladyship", "ladyship", "ladyship", "lancast", "lancast", "lancast", "lancast", "land", "land", "land", "land", "land", "land", "land", "land", "land", "land", "le", "leav", "leav", "leav", "leav", "leav", "leav", "leav", "leav", "leav", "leav", "leek", "letter", "letter", "letter", "letter", "letter", "letter", "letter", "letter", "letter", "letter", "licio", "life", "life", "life", "life", "life", "life", "life", "life", "life", "life", "light", "light", "light", "light", "light", "light", "light", "light", "light", "light", "lionel", "live", "live", "live", "live", "live", "live", "live", "live", "live", "live", "love", "love", "love", "love", "love", "love", "love", "love", "love", "love", "mad", "mad", "mad", "mad", "mad", "mad", "mad", "mad", "mad", "mad", "madam", "madam", "madam", "madam", "madam", "madam", "madam", "madam", "madam", "madam", "madonna", "marri", "marri", "marri", "marri", "marri", "marri", "marri", "marri", "marri", "marri", "messina", "milford", "monster", "monster", "monster", "monster", "monster", "monster", "monster", "monster", "montagu", "montgomeri", "moor", "moor", "moor", "mytilen", "napl", "napl", "napl", "narbon", "natur", "natur", "natur", "natur", "natur", "natur", "natur", "natur", "natur", "natur", "navarr", "night", "night", "night", "night", "night", "night", "night", "night", "night", "night", "nightwork", "nobl", "nobl", "nobl", "nobl", "nobl", "nobl", "nobl", "nobl", "nobl", "nobl", "norwai", "norwai", "nuncl", "nunneri", "oman", "padua", "padua", "peac", "peac", "peac", "peac", "peac", "peac", "peac", "peac", "peac", "peac", "phaethon", "philippi", "philippi", "pisa", "plai", "plai", "plai", "plai", "plai", "plai", "plai", "plai", "plai", "plai", "polack", "polydor", "pompeiu", "poor", "poor", "poor", "poor", "poor", "poor", "poor", "poor", "poor", "poor", "prai", "prai", "prai", "prai", "prai", "prai", "prai", "prai", "prai", "prai", "protector", "protector", "quoth", "quoth", "quoth", "quoth", "quoth", "quoth", "quoth", "quoth", "rapin", "realm", "realm", "realm", "realm", "realm", "regent", "regent", "report", "report", "report", "report", "report", "report", "report", "report", "report", "repossess", "requiem", "rome", "rome", "rome", "rome", "rome", "rome", "rousillon", "ruler", "salad", "saliqu", "saturnin", "scot", "scot", "seigneur", "senat", "senat", "senat", "senat", "senior", "senior", "shall", "sherri", "shout", "shout", "shout", "shout", "shout", "shout", "sicilia", "sicyon", "signior", "signior", "signior", "signior", "signior", "sister", "sister", "sister", "sister", "sister", "sister", "sister", "sister", "sister", "sister", "slew", "slew", "slew", "slew", "slew", "slew", "sola", "son", "son", "son", "son", "son", "son", "son", "son", "son", "son", "soul", "soul", "soul", "soul", "soul", "soul", "soul", "soul", "soul", "soul", "southwel", "spendthrift", "stabb", "stabb", "stand", "stand", "stand", "stand", "stand", "stand", "stand", "stand", "stand", "stand", "swagger", "swagger", "swagger", "swagger", "sweet", "sweet", "sweet", "sweet", "sweet", "sweet", "sweet", "sweet", "sweet", "sweet", "sycorax", "syracusa", "syracusian", "tarpeian", "tarsu", "tent", "tent", "tent", "tent", "tent", "tent", "tent", "tent", "thane", "thisb", "thisbi", "thursdai", "thursdai", "tiber", "topa", "tower", "tower", "tower", "tower", "tower", "tower", "tower", "traitor", "traitor", "traitor", "traitor", "traitor", "traitor", "traitor", "traitor", "traitor", "traitor", "troi", "troi", "troi", "troi", "troi", "troi", "trojan", "trojan", "true", "true", "true", "true", "true", "true", "true", "true", "true", "true", "tuni", "tyre", "vill", "volsc", "volscian", "voltimand", "vou", "vou", "willow", "willow", "willow", "wit", "wit", "wit", "wit", "wit", "wit", "wit", "wit", "wit", "wit", "woe", "woe", "woe", "woe", "woe", "woe", "woe", "woe", "woe", "woman", "woman", "woman", "woman", "woman", "woman", "woman", "woman", "woman", "woman", "word", "word", "word", "word", "word", "word", "word", "word", "word", "word", "world", "world", "world", "world", "world", "world", "world", "world", "world", "world", "wrestler", "youth", "youth", "youth", "youth", "youth", "youth", "youth", "youth", "youth", "youth" ],
"Topic": [ 4, 8, 4, 4, 2, 9, 9, 10, 7, 5, 9, 9, 10, 7, 6, 6, 1, 2, 3, 4, 5, 6, 7, 8, 9, 10, 7, 3, 3, 8, 10, 10, 2, 9, 5, 7, 5, 3, 6, 8, 1, 2, 3, 4, 5, 6, 7, 8, 9, 10, 7, 1, 2, 3, 4, 5, 6, 7, 8, 9, 1, 8, 2, 3, 1, 2, 3, 4, 5, 6, 7, 8, 9, 10, 2, 5, 4, 2, 2, 5, 1, 4, 5, 6, 7, 8, 9, 10, 8, 8, 1, 2, 3, 4, 5, 6, 7, 8, 9, 10, 2, 8, 2, 7, 10, 4, 3, 3, 3, 1, 1, 2, 3, 4, 5, 6, 7, 8, 10, 5, 1, 3, 6, 10, 4, 4, 7, 7, 3, 2, 3, 10, 2, 1, 2, 3, 4, 5, 6, 7, 1, 2, 3, 4, 5, 6, 7, 8, 9, 10, 3, 1, 2, 3, 4, 5, 6, 7, 8, 9, 10, 6, 1, 2, 3, 4, 5, 6, 7, 8, 9, 1, 2, 3, 4, 5, 6, 7, 8, 9, 10, 6, 5, 5, 6, 1, 2, 4, 6, 8, 3, 3, 8, 1, 2, 3, 5, 6, 7, 8, 9, 1, 3, 7, 9, 1, 3, 5, 6, 7, 8, 9, 10, 4, 1, 2, 3, 4, 5, 6, 7, 8, 9, 10, 1, 2, 3, 4, 5, 6, 7, 8, 9, 10, 2, 8, 1, 2, 3, 4, 5, 6, 7, 8, 9, 10, 1, 2, 3, 4, 5, 6, 7, 8, 9, 10, 2, 9, 10, 1, 2, 3, 4, 5, 6, 7, 8, 9, 10, 1, 2, 3, 4, 5, 6, 7, 8, 9, 10, 10, 3, 8, 8, 5, 3, 3, 1, 2, 3, 4, 5, 6, 7, 8, 9, 10, 1, 2, 3, 4, 5, 6, 7, 8, 9, 10, 4, 1, 2, 3, 4, 5, 6, 7, 8, 9, 10, 1, 5, 9, 10, 1, 9, 4, 7, 8, 9, 10, 9, 9, 10, 1, 2, 3, 4, 5, 6, 7, 8, 9, 10, 2, 3, 5, 7, 9, 10, 1, 2, 3, 4, 5, 6, 7, 8, 9, 10, 1, 2, 3, 4, 5, 6, 7, 8, 9, 10, 1, 2, 3, 4, 5, 6, 7, 8, 9, 10, 5, 7, 10, 8, 1, 2, 3, 4, 5, 6, 7, 8, 9, 10, 1, 2, 3, 4, 5, 6, 7, 8, 9, 10, 1, 2, 3, 4, 5, 6, 7, 8, 9, 10, 10, 1, 6, 7, 10, 5, 6, 7, 9, 3, 3, 5, 6, 7, 9, 1, 2, 7, 9, 1, 9, 10, 1, 7, 1, 1, 2, 3, 5, 6, 7, 5, 7, 9, 10, 1, 2, 3, 4, 5, 6, 7, 8, 9, 10, 9, 1, 2, 3, 4, 5, 6, 7, 8, 9, 10, 9, 1, 2, 3, 4, 5, 6, 7, 8, 9, 10, 8, 1, 2, 3, 4, 5, 6, 7, 8, 9, 10, 1, 2, 3, 4, 5, 6, 7, 8, 9, 10, 7, 1, 2, 3, 4, 5, 6, 7, 8, 9, 10, 1, 2, 3, 4, 5, 6, 7, 8, 9, 10, 1, 2, 3, 4, 5, 6, 7, 8, 9, 10, 1, 2, 3, 4, 5, 6, 7, 8, 9, 10, 1, 1, 2, 3, 4, 5, 6, 7, 8, 9, 10, 1, 2, 1, 2, 3, 4, 5, 6, 8, 9, 4, 5, 3, 7, 10, 9, 5, 6, 7, 3, 1, 2, 3, 4, 5, 6, 7, 8, 9, 10, 1, 1, 2, 3, 4, 5, 6, 7, 8, 9, 10, 10, 1, 2, 3, 4, 5, 6, 7, 8, 9, 10, 3, 6, 6, 6, 8, 1, 8, 1, 2, 3, 4, 5, 6, 7, 8, 9, 10, 5, 3, 10, 8, 1, 2, 3, 4, 5, 6, 7, 8, 9, 10, 6, 2, 3, 1, 2, 3, 4, 5, 6, 7, 8, 9, 10, 1, 2, 3, 4, 5, 6, 7, 8, 9, 10, 5, 7, 1, 3, 4, 5, 6, 8, 9, 10, 7, 5, 6, 7, 9, 10, 7, 9, 1, 2, 3, 4, 5, 6, 7, 8, 10, 5, 6, 2, 3, 4, 5, 7, 10, 3, 7, 3, 9, 7, 9, 10, 9, 2, 3, 7, 10, 1, 8, 2, 10, 1, 3, 5, 8, 9, 10, 2, 3, 1, 2, 3, 7, 8, 1, 2, 3, 4, 5, 6, 7, 8, 9, 10, 1, 2, 3, 4, 5, 7, 1, 1, 2, 3, 4, 5, 6, 7, 8, 9, 10, 1, 2, 3, 4, 5, 6, 7, 8, 9, 10, 7, 6, 1, 5, 1, 2, 3, 4, 5, 6, 7, 8, 9, 10, 1, 8, 9, 10, 1, 2, 3, 4, 5, 6, 7, 8, 9, 10, 6, 4, 4, 2, 9, 1, 2, 3, 4, 5, 7, 9, 10, 3, 8, 8, 4, 9, 10, 1, 1, 3, 4, 5, 6, 7, 9, 1, 2, 3, 4, 5, 6, 7, 8, 9, 10, 1, 4, 5, 7, 9, 10, 4, 9, 1, 2, 3, 4, 5, 6, 7, 8, 9, 10, 6, 9, 8, 2, 2, 6, 1, 9, 1, 3, 5, 1, 2, 3, 4, 5, 6, 7, 8, 9, 10, 1, 2, 3, 4, 5, 6, 7, 9, 10, 1, 2, 3, 4, 5, 6, 7, 8, 9, 10, 1, 2, 3, 4, 5, 6, 7, 8, 9, 10, 1, 2, 3, 4, 5, 6, 7, 8, 9, 10, 8, 1, 2, 3, 4, 5, 6, 7, 8, 9, 10 ],
"Freq": [ 1.0763, 1.3448, 0.85291, 1.0091, 1.4144, 0.6902, 1.3804, 1.4051, 0.72405, 0.97165, 0.92027, 0.92031, 0.70254, 1.4481,  1.358,  1.358, 0.044702, 0.072641, 0.061466, 0.067053, 0.19557, 0.094992, 0.1844, 0.033527, 0.15646, 0.083817, 0.9654, 0.92024, 0.051124, 0.35786, 0.56236, 0.70254, 1.1315, 1.0353, 0.95511, 0.9654, 1.5789, 0.084352, 0.084352, 0.75917, 0.090533, 0.11226, 0.086911, 0.1014, 0.10864, 0.090533, 0.094154, 0.10502, 0.065184, 0.14123, 0.89114, 0.1646, 0.060642, 0.043316, 0.47647, 0.060642, 0.051979, 0.034652, 0.060642, 0.060642, 0.87133, 1.3448, 0.94295, 1.1043, 0.090045, 0.082215, 0.09396, 0.082215, 0.21533, 0.043065, 0.13703, 0.019575, 0.12528, 0.10962, 0.97922, 0.78946, 1.3454, 0.91081, 0.9901, 1.2631, 0.058748, 0.029374, 0.088122, 0.058748, 0.088122, 0.58748, 0.029374, 0.058748, 0.89946, 0.94304, 0.040212, 0.20106, 0.20106, 0.030159, 0.040212, 0.24127, 0.030159, 0.080424, 0.060318, 0.070371, 0.80825, 1.1527, 0.068694, 0.068694, 0.75564, 1.0764, 1.1832, 1.0353, 1.0517, 1.0166, 0.068145, 0.034072, 0.034072, 0.54516, 0.034072, 0.034072, 0.068145, 0.20443, 0.034072, 1.0526, 0.95054, 1.1832, 0.67899, 0.93671, 0.96871, 1.0091, 0.72405, 0.8668, 0.92024, 0.86763, 0.072303,  1.124, 0.94295, 0.43106, 0.061579, 0.28737, 0.082106, 0.082106, 0.020526, 0.020526, 0.029297, 0.051269, 0.065918, 0.021973, 0.30762, 0.065918, 0.16113, 0.051269, 0.13916, 0.08789, 0.99481, 0.1144, 0.070931, 0.073219, 0.11898, 0.15559, 0.061779, 0.0961, 0.082371, 0.12585, 0.10068, 0.90533, 0.049344, 0.049344, 0.049344, 0.049344, 0.098689, 0.54279, 0.049344, 0.098689, 0.049344, 0.076001, 0.12667, 0.090076, 0.14356, 0.1886, 0.067557, 0.15763, 0.030964, 0.050668, 0.064742, 0.98763,  1.015, 1.0526, 0.84889, 0.65081, 0.046486, 0.13946, 0.046486, 0.092973, 0.92024, 0.93843, 0.058652, 0.05522, 0.082831, 0.11044, 0.02761, 0.05522, 0.60742, 0.02761, 0.02761, 0.057272, 0.057272, 0.85908, 0.057272, 0.0094267, 0.02828, 0.29223, 0.11312, 0.29223, 0.0094267, 0.21681, 0.047134, 1.1532, 0.14112, 0.086843, 0.075987, 0.26053, 0.097698, 0.089014, 0.06079, 0.071645, 0.073816, 0.043421, 0.20021, 0.08073, 0.064584, 0.19052, 0.10011, 0.064584, 0.048438, 0.10011, 0.11625, 0.035521, 0.084666, 0.84666, 0.2044, 0.078153, 0.1022, 0.030059, 0.096189, 0.072142, 0.036071, 0.11422, 0.16833, 0.090177, 0.079878, 0.13609, 0.11242, 0.11538, 0.13905, 0.079878, 0.097629, 0.059169, 0.085795, 0.094671, 1.0239, 1.1832,  1.124, 0.12811, 0.10142, 0.1975, 0.048041, 0.10676, 0.090744, 0.058717, 0.080069, 0.058717, 0.13345, 0.12931, 0.096229, 0.11126, 0.060143, 0.12931, 0.081193, 0.072172, 0.069165, 0.057136, 0.19246, 0.93671, 1.0736, 1.0086, 1.0411, 1.0526, 0.92024, 1.0353, 0.10824, 0.086148, 0.075103, 0.022089, 0.15462, 0.06185, 0.11486, 0.059641, 0.13916, 0.17671, 0.047585, 0.15465, 0.083274, 0.083274, 0.047585, 0.011896, 0.095171, 0.11896, 0.047585, 0.3093, 0.9785, 0.16254, 0.11784, 0.077205, 0.052824, 0.13816, 0.14222, 0.12597, 0.032507, 0.069078, 0.081268, 0.19327, 0.67645, 0.096636, 0.93671, 0.085975, 0.85975, 0.048533, 0.048533, 0.048533, 0.72799, 0.048533, 0.92027, 0.87754, 0.13501, 0.10815, 0.094341, 0.11505, 0.082836, 0.15877, 0.071331, 0.13346, 0.085137, 0.075933, 0.078234, 0.079265, 0.87192, 0.095792, 0.071844, 0.50291, 0.31132, 0.12572, 0.14712, 0.11235, 0.053499, 0.10432, 0.098974, 0.048149, 0.10967, 0.077574, 0.12037, 0.12943, 0.084234, 0.10478, 0.13149, 0.10889, 0.084234, 0.11094, 0.076016, 0.069853, 0.10067, 0.09482, 0.15367, 0.14714, 0.078472, 0.14387, 0.14387, 0.088281, 0.062124, 0.052315, 0.039236, 0.1624, 0.81201, 0.081201, 0.89654, 0.082952, 0.25676, 0.1264, 0.051351, 0.067151, 0.075052, 0.1027, 0.047401, 0.098752, 0.094802, 0.13468, 0.11785, 0.078565, 0.022447, 0.0954, 0.044894, 0.084176, 0.25253, 0.039282, 0.12907, 0.12613, 0.11871, 0.14097, 0.10387, 0.10387, 0.066776, 0.029678, 0.25969, 0.022259, 0.029678, 0.81016, 1.0456, 1.0864, 0.17512, 0.70046, 0.1875, 0.093749, 0.65624, 0.093749, 1.0353, 0.071174, 0.071174, 0.56939, 0.071174, 0.14235, 0.74918, 0.083242, 0.083242, 0.16648, 0.96536, 0.034477, 0.93671, 0.93328, 0.15555, 0.98025, 0.65986, 0.059987, 0.11997, 0.059987, 0.059987, 0.11997, 0.31866, 0.14484, 0.11587, 0.43453, 0.019393, 0.087269, 0.11636, 0.0096965, 0.2812, 0.11636, 0.096965, 0.096965, 0.096965, 0.077572, 1.0061, 0.11712, 0.14551, 0.11712, 0.070981, 0.11712, 0.088726, 0.10292, 0.10292, 0.067432, 0.070981, 0.91892, 0.31082, 0.098553, 0.11371, 0.022743, 0.045486, 0.1213, 0.053067, 0.1213, 0.022743, 0.090972, 1.1527, 0.10372, 0.16891, 0.091864, 0.10668, 0.10668, 0.10075, 0.11261, 0.077047, 0.068157, 0.068157, 0.17087, 0.052004, 0.13372, 0.26002, 0.066862, 0.089149, 0.037146, 0.059433, 0.044575, 0.08172, 1.1585, 0.13006, 0.11622, 0.099619, 0.14113, 0.14113, 0.074714, 0.11069, 0.035973, 0.060878, 0.091317, 0.24725, 0.059228, 0.096833, 0.18332, 0.07709, 0.064868, 0.042305, 0.12786, 0.053587, 0.047946, 0.13584, 0.079908, 0.071917, 0.11986, 0.047945, 0.20776, 0.079908, 0.15982, 0.055936, 0.055936, 0.25633, 0.11509, 0.21971, 0.0052312, 0.12032, 0.12032, 0.094162, 0.036619, 0.026156, 0.0052312, 1.0456, 0.20398, 0.09689, 0.12239, 0.015298, 0.066293, 0.061194, 0.040796, 0.29067, 0.030597, 0.066293, 0.87133, 0.94844, 0.028521, 0.085564, 0.085564, 0.028521, 0.028521, 0.59895, 0.085564, 0.057042, 1.0764, 0.78946, 0.76684, 0.20914, 0.034857,  1.004, 0.092599, 0.74079, 0.1852, 0.92024, 0.082148, 0.17525, 0.1862, 0.082148, 0.043812, 0.1862, 0.027383, 0.043812, 0.060242, 0.11501, 0.87133, 0.10484, 0.051003, 0.15868, 0.18985, 0.085006, 0.10484, 0.042503, 0.093506, 0.073671, 0.09634, 0.93671, 0.037041, 0.16463, 0.13582, 0.0041157, 0.11936, 0.10289, 0.13993, 0.02881, 0.069967, 0.20167, 0.18166, 0.72663, 0.95858, 1.0864, 0.89654, 0.18439, 0.82975, 0.11005, 0.11505, 0.070031, 0.015007, 0.18008, 0.060027, 0.12506, 0.065029, 0.095042, 0.16507, 0.78946, 0.20059, 0.80237, 0.96058, 0.1565, 0.091295, 0.084773, 0.045647, 0.06521, 0.18911, 0.039126, 0.19563, 0.097816, 0.032605, 1.0864, 1.1315, 0.92024, 0.081433, 0.14251, 0.11808, 0.13029, 0.093648, 0.13029, 0.065147, 0.07329, 0.069218, 0.09772, 0.15049, 0.16759, 0.11629, 0.017101, 0.037622, 0.11629, 0.044462, 0.19153, 0.054723, 0.10261, 0.20322, 0.81289, 0.099261, 0.049631, 0.54594, 0.074446, 0.024815, 0.099261, 0.074446, 0.024815, 0.72405, 0.096135, 0.096135, 0.62488, 0.096135, 0.048068, 0.86063, 0.14344, 0.044883, 0.3441, 0.25434, 0.029922, 0.059844, 0.059844, 0.059844, 0.074805, 0.059844, 0.78946,  1.358, 0.23719, 0.10035, 0.036491, 0.036491, 0.33754, 0.24632, 1.0618, 0.82749, 0.92024, 0.92027, 1.0861, 0.88649, 0.11081, 1.0353, 0.13389, 0.10042, 0.033473, 0.73641, 0.19563, 0.78252, 0.94295, 1.1241, 0.062748, 0.062748, 0.1255, 0.062748, 0.062748, 0.62748,  1.012, 0.92024, 0.43569, 0.059412, 0.09902, 0.019804, 0.39608, 0.086552, 0.12365, 0.098917, 0.024729, 0.049458, 0.24729, 0.049458, 0.23493, 0.049458, 0.049458, 0.14131, 0.070655, 0.070655, 0.070655, 0.56524, 0.070655, 1.0456, 0.0375, 0.1125, 0.0375, 0.0375,   0.15, 0.01875, 0.46875, 0.01875, 0.05625, 0.05625, 0.12708, 0.070599, 0.094132, 0.089426, 0.22121, 0.11296, 0.11767, 0.037653, 0.089426, 0.032946, 0.72405,  1.358, 0.20365, 0.81459, 0.091982, 0.13797, 0.088444, 0.06368, 0.1309, 0.095519, 0.088444, 0.077831, 0.095519, 0.1309, 0.12601, 0.12601, 0.12601, 0.63007, 0.20481, 0.05896, 0.065166, 0.17998, 0.080682, 0.062063, 0.083785, 0.12413, 0.099301, 0.037238,  1.164, 0.67272, 1.0091, 1.1315, 1.0354, 0.055266, 0.027633, 0.055266, 0.027633, 0.19343, 0.027633, 0.44213, 0.13816, 0.97961, 0.94001, 1.0202, 0.79588, 0.15918, 0.70098, 0.98025, 0.034444, 0.034444, 0.068888, 0.44777, 0.13778, 0.24111, 0.034444, 0.026967, 0.094386, 0.067418, 0.026967, 0.17529, 0.10787, 0.32361, 0.026967, 0.080902, 0.067418, 0.030873, 0.12349, 0.030873, 0.092618, 0.64833, 0.030873, 0.060032, 0.90049, 0.16277, 0.1465, 0.078132, 0.11069, 0.10418, 0.071621, 0.06511, 0.091154, 0.094409, 0.081387, 0.90533, 1.0353, 1.0759, 0.99009, 1.1315, 1.0864, 0.10183, 0.91646, 0.11062, 0.77434, 0.11062, 0.33866, 0.062521, 0.057311, 0.1042, 0.041681, 0.078152, 0.083362, 0.088572, 0.078152, 0.067732, 0.062273, 0.062273, 0.024909,  0.411, 0.14945, 0.087182,  0.137, 0.024909, 0.012455, 0.15601, 0.16251, 0.13651, 0.032501, 0.052002, 0.065003, 0.058503, 0.24701, 0.026001, 0.058503, 0.1641, 0.10076, 0.077731, 0.077731, 0.10652, 0.069094, 0.10076, 0.10364, 0.077731, 0.11804, 0.13251, 0.10913, 0.14031, 0.10133, 0.11692, 0.085743, 0.062359, 0.093538, 0.077948, 0.081846, 1.1527, 0.29145, 0.099925, 0.083271, 0.10825, 0.041636, 0.049963, 0.074944, 0.091598, 0.083271, 0.083271 ] 
},
"R":     10,
"lambda.step":   0.01,
"plot.opts": {
 "xlab": "PC1",
"ylab": "PC2" 
},
"topic.order": [ 9, 2, 7, 6, 3, 1, 10, 8, 5, 4 ] 
}